cyylog/CyLog.py
cyylog/__init__.py
CyyLog-0.0.5.dist-info/LICENSE
CyyLog-0.0.5.dist-info/METADATA
CyyLog-0.0.5.dist-info/WHEEL
CyyLog-0.0.5.dist-info/top_level.txt
CyyLog-0.0.5.dist-info/RECORD
