Metadata-Version: 2.1
Name: CyyLog
Version: 0.0.5
Summary: library used to manage file queues
Author: ryyos (Rio Dwi Saputra)
Author-email: <riodwi12174@gmail.com>
Keywords: log,logger,queque
Classifier: Development Status :: 1 - Planning
Classifier: Intended Audience :: Developers
Classifier: Programming Language :: Python
Classifier: Operating System :: Microsoft :: Windows
License-File: LICENSE
Requires-Dist: click
